{"chunk_definitions":[{"row":17,"row_count":1,"visible":true,"expansion_state":0,"options":{"engine":"r","label":"unnamed-chunk-3","dev":"png"},"document_id":"19E10C47","chunk_id":"c106onslyr81p","chunk_label":"unnamed-chunk-1"},{"row":56,"row_count":1,"visible":true,"expansion_state":0,"options":{"engine":"r","label":"unnamed-chunk-4","dev":"png"},"document_id":"8C98DADF","chunk_id":"c1ipuhes7jaap","chunk_label":"unnamed-chunk-3"},{"row":71,"row_count":1,"visible":true,"expansion_state":0,"options":{"engine":"r","label":"unnamed-chunk-20","dev":"png"},"document_id":"8C98DADF","chunk_id":"cof94wktqff7s","chunk_label":"unnamed-chunk-4"},{"row":87,"row_count":1,"visible":true,"expansion_state":0,"options":{"engine":"r","label":"unnamed-chunk-5","dev":"png"},"document_id":"19E10C47","chunk_id":"coua6d0da1l1u","chunk_label":"unnamed-chunk-5"},{"row":102,"row_count":1,"visible":true,"expansion_state":0,"options":{"engine":"r","label":"unnamed-chunk-6","dev":"png"},"document_id":"19E10C47","chunk_id":"cb17ye00ybr80","chunk_label":"unnamed-chunk-6"},{"row":185,"row_count":1,"visible":true,"expansion_state":0,"options":{"engine":"r","label":"unnamed-chunk-9","dev":"png"},"document_id":"19E10C47","chunk_id":"cgy293ljkxu36","chunk_label":"unnamed-chunk-7"}],"doc_write_time":1731681109,"chunk_rendered_width":666}